CHANGELOG
MANIFEST.in
README.rst
setup.py
PyMarvelSimple.egg-info/PKG-INFO
PyMarvelSimple.egg-info/SOURCES.txt
PyMarvelSimple.egg-info/dependency_links.txt
PyMarvelSimple.egg-info/entry_points.txt
PyMarvelSimple.egg-info/pbr.json
PyMarvelSimple.egg-info/requires.txt
PyMarvelSimple.egg-info/top_level.txt
docs/Makefile
docs/make.bat
docs/build/doctrees/api.doctree
docs/build/doctrees/environment.pickle
docs/build/doctrees/index.doctree
docs/source/api.rst
docs/source/conf.py
docs/source/index.rst
pymarvelsimple/__init__.py
pymarvelsimple/marvel.py
tests/characters.py