Metadata-Version: 1.1
Name: PyMarvelSimple
Version: 0.3
Summary: A wrapper for marvel API.
Home-page: UNKNOWN
Author: Hobbestigrou
Author-email: hobbestigrou@erakis.eu
License: MIT
Keywords: marvel,requests
Platform: UNKNOWN
Classifier: Development Status :: 4 - Beta
Classifier: Intended Audience :: Developers
Classifier: License :: OSI Approved :: MIT License
Classifier: Natural Language :: English
Classifier: Operating System :: Unix
Classifier: Programming Language :: Python :: 2.7
Classifier: Programming Language :: Python :: 3.4
Classifier: Programming Language :: Python :: Implementation :: PyPy
Classifier: Operating System :: OS Independent
